{
  "actions": [
    {
      "acted_at": "2019-05-14", 
      "action_code": "Intro-H", 
      "references": [], 
      "text": "Introduced in House", 
      "type": "action"
    }, 
    {
      "acted_at": "2019-05-14", 
      "action_code": "H11100", 
      "committees": [
        "HSJU"
      ], 
      "references": [], 
      "status": "REFERRED", 
      "text": "Referred to the House Committee on the Judiciary.", 
      "type": "referral"
    }
  ], 
  "amendments": [], 
  "bill_id": "hr2731-116", 
  "bill_type": "hr", 
  "by_request": false, 
  "committee_reports": [], 
  "committees": [
    {
      "activity": [
        "referral"
      ], 
      "committee": "House Judiciary", 
      "committee_id": "HSJU"
    }
  ], 
  "congress": "116", 
  "cosponsors": [
    {
      "bioguide_id": "L000397", 
      "district": "19", 
      "name": "Lofgren, Zoe", 
      "original_cosponsor": true, 
      "sponsored_at": "2019-05-14", 
      "state": "CA", 
      "title": "Rep", 
      "withdrawn_at": null
    }, 
    {
      "bioguide_id": "S000522", 
      "district": "4", 
      "name": "Smith, Christopher H.", 
      "original_cosponsor": true, 
      "sponsored_at": "2019-05-14", 
      "state": "NJ", 
      "title": "Rep", 
      "withdrawn_at": null
    }, 
    {
      "bioguide_id": "W000810", 
      "district": "7", 
      "name": "Woodall, Rob", 
      "original_cosponsor": true, 
      "sponsored_at": "2019-05-14", 
      "state": "GA", 
      "title": "Rep", 
      "withdrawn_at": null
    }
  ], 
  "enacted_as": null, 
  "history": {
    "active": false, 
    "awaiting_signature": false, 
    "enacted": false, 
    "vetoed": false
  }, 
  "introduced_at": "2019-05-14", 
  "number": "2731", 
  "official_title": "To provide for automatic acquisition of United States citizenship for certain internationally adopted individuals, and for other purposes.", 
  "popular_title": null, 
  "related_bills": [], 
  "short_title": "Adoptee Citizenship Act of 2019", 
  "sponsor": {
    "bioguide_id": "S000510", 
    "district": "9", 
    "name": "Smith, Adam", 
    "state": "WA", 
    "title": "Rep", 
    "type": "person"
  }, 
  "status": "REFERRED", 
  "status_at": "2019-05-14", 
  "subjects": [], 
  "subjects_top_term": null, 
  "summary": null, 
  "titles": [
    {
      "as": "introduced", 
      "is_for_portion": false, 
      "title": "To provide for automatic acquisition of United States citizenship for certain internationally adopted individuals, and for other purposes.", 
      "type": "official"
    }, 
    {
      "as": "introduced", 
      "is_for_portion": false, 
      "title": "Adoptee Citizenship Act of 2019", 
      "type": "short"
    }, 
    {
      "as": "introduced", 
      "is_for_portion": false, 
      "title": "Adoptee Citizenship Act of 2019", 
      "type": "short"
    }, 
    {
      "as": null, 
      "is_for_portion": false, 
      "title": "Adoptee Citizenship Act of 2019", 
      "type": "display"
    }
  ], 
  "updated_at": "2019-05-29T13:30:09Z", 
  "url": "https://www.govinfo.gov/bulkdata/BILLSTATUS/116/hr/BILLSTATUS-116hr2731.xml"
}