{
  "actions": [
    {
      "acted_at": "2019-04-03", 
      "action_code": "Intro-H", 
      "references": [], 
      "text": "Introduced in House", 
      "type": "action"
    }, 
    {
      "acted_at": "2019-04-03", 
      "action_code": "H11100", 
      "committees": [
        "HSIF"
      ], 
      "references": [], 
      "status": "REFERRED", 
      "text": "Referred to the House Committee on Energy and Commerce.", 
      "type": "referral"
    }
  ], 
  "amendments": [], 
  "bill_id": "hr2078-116", 
  "bill_type": "hr", 
  "by_request": false, 
  "committee_reports": [], 
  "committees": [
    {
      "activity": [
        "referral"
      ], 
      "committee": "House Energy and Commerce", 
      "committee_id": "HSIF"
    }
  ], 
  "congress": "116", 
  "cosponsors": [], 
  "enacted_as": null, 
  "history": {
    "active": false, 
    "awaiting_signature": false, 
    "enacted": false, 
    "vetoed": false
  }, 
  "introduced_at": "2019-04-03", 
  "number": "2078", 
  "official_title": "To prohibit the sale of food that is, or contains, unsafe poppy seeds.", 
  "popular_title": null, 
  "related_bills": [], 
  "short_title": "Stephen Hacala Poppy Seed Safety Act", 
  "sponsor": {
    "bioguide_id": "W000809", 
    "district": "3", 
    "name": "Womack, Steve", 
    "state": "AR", 
    "title": "Rep", 
    "type": "person"
  }, 
  "status": "REFERRED", 
  "status_at": "2019-04-03", 
  "subjects": [], 
  "subjects_top_term": null, 
  "summary": null, 
  "titles": [
    {
      "as": "introduced", 
      "is_for_portion": false, 
      "title": "To prohibit the sale of food that is, or contains, unsafe poppy seeds.", 
      "type": "official"
    }, 
    {
      "as": "introduced", 
      "is_for_portion": false, 
      "title": "Stephen Hacala Poppy Seed Safety Act", 
      "type": "short"
    }, 
    {
      "as": "introduced", 
      "is_for_portion": false, 
      "title": "Stephen Hacala Poppy Seed Safety Act", 
      "type": "short"
    }, 
    {
      "as": null, 
      "is_for_portion": false, 
      "title": "Stephen Hacala Poppy Seed Safety Act", 
      "type": "display"
    }
  ], 
  "updated_at": "2019-04-17T13:15:08Z", 
  "url": "https://www.govinfo.gov/bulkdata/BILLSTATUS/116/hr/BILLSTATUS-116hr2078.xml"
}